{"index": "AL061913", "name": "UNNAMED", "recordCount": 10, "Date": ["19131028", "19131028", "19131028", "19131028", "19131029", "19131029", "19131029", "19131029", "19131030", "19131030"], "Time": ["0000", "0600", "1200", "1800", "0000", "0600", "1200", "1800", "0000", "0600"], "Record_identifier": ["", "", "", "", "", "", "", "", "", ""], "Status_of_system": ["TS", "TS", "TS", "TS", "HU", "HU", "TS", "TS", "TS", "EX"], "Latitude": [18.0, 19.0, 20.0, 21.0, 21.5, 21.8, 22.0, 22.2, 22.5, 22.8], "Longitude": [-86.5, -86.3, -86.0, -85.5, -85.1, -84.8, -84.4, -84.0, -83.3, -82.3], "Maximum_sustained_wind": [35, 40, 45, 55, 65, 65, 55, 40, 35, 30], "Minimum_Pressure": [-999, -999, -999, -999, -999, -999, -999, 1003, -999, -999]}