{"index": "AL111944", "name": "UNNAMED", "recordCount": 13, "Date": ["19440930", "19440930", "19440930", "19441001", "19441001", "19441001", "19441001", "19441002", "19441002", "19441002", "19441002", "19441003", "19441003"], "Time": ["0600", "1200", "1800", "0000", "0600", "1200", "1800", "0000", "0600", "1200", "1800", "0000", "0600"], "Record_identifier": ["", "", "", "", "", "", "", "", "", "", "", "", ""], "Status_of_system": ["TS", "TS", "TS", "TS", "TS", "TS", "TS", "TS", "TS", "TS", "TS", "TS", "TD"], "Latitude": [14.4, 14.5, 14.6, 14.8, 15.0, 15.3, 15.8, 16.6, 17.8, 18.9, 19.8, 20.3, 20.5], "Longitude": [-59.3, -59.5, -59.7, -59.9, -60.2, -60.7, -61.1, -61.0, -60.5, -59.7, -59.2, -59.0, -59.0], "Maximum_sustained_wind": [35, 40, 40, 40, 40, 40, 40, 40, 40, 40, 35, 35, 30], "Minimum_Pressure": [-999, -999, -999, -999, -999, -999, -999, -999, -999, -999, -999, -999, -999]}