{"index": "AL071974", "name": "ALMA", "recordCount": 13, "Date": ["19740812", "19740812", "19740813", "19740813", "19740813", "19740813", "19740814", "19740814", "19740814", "19740814", "19740815", "19740815", "19740815"], "Time": ["1200", "1800", "0000", "0600", "1200", "1800", "0000", "0600", "1200", "1800", "0000", "0600", "1200"], "Record_identifier": ["", "", "", "", "", "", "", "", "", "", "", "", ""], "Status_of_system": ["TD", "TD", "TD", "TD", "TS", "TS", "TS", "TS", "TS", "TS", "TS", "TS", "TS"], "Latitude": [10.5, 10.4, 10.3, 10.2, 10.1, 10.0, 10.1, 10.1, 10.2, 10.3, 10.4, 10.5, 10.5], "Longitude": [-43.0, -45.3, -47.5, -49.8, -52.0, -54.0, -56.5, -58.5, -60.5, -63.0, -65.5, -67.5, -70.0], "Maximum_sustained_wind": [25, 25, 25, 30, 35, 55, 50, 45, 40, 35, 35, 35, 35], "Minimum_Pressure": [1010, -999, -999, -999, -999, 1007, -999, -999, -999, -999, -999, -999, -999]}