{"index": "AL081981", "name": "UNNAMED", "recordCount": 7, "Date": ["19810725", "19810725", "19810725", "19810726", "19810726", "19810726", "19810726"], "Time": ["0600", "1200", "1800", "0000", "0600", "1200", "1800"], "Record_identifier": ["", "", "", "", "", "", ""], "Status_of_system": ["TD", "TD", "TD", "TD", "TD", "TD", "TD"], "Latitude": [23.3, 23.8, 24.0, 24.3, 24.8, 25.0, 25.4], "Longitude": [-91.8, -93.0, -94.1, -95.2, -96.7, -98.0, -99.3], "Maximum_sustained_wind": [20, 25, 25, 30, 30, 25, -99], "Minimum_Pressure": [-999, -999, -999, -999, -999, -999, -999]}